pdf2s/__init__.py
pdf2s/cli.py
pdf2s/converters/__init__.py
pdf2s/converters/md_pdf.py
pdf2s/converters/pdf_img.py
pdf2s/converters/pdf_md.py
pdf2s/converters/pdf_merger.py
pdf2s/converters/pdf_splitter.py
pdf2s-0.1.2.dist-info/LICENSE
pdf2s-0.1.2.dist-info/METADATA
pdf2s-0.1.2.dist-info/WHEEL
pdf2s-0.1.2.dist-info/entry_points.txt
pdf2s-0.1.2.dist-info/top_level.txt
pdf2s-0.1.2.dist-info/RECORD
