Metadata-Version: 2.2
Name: pdf2s
Version: 0.1.2
Summary: Extended PDF Manipulation Toolkit
Author-email: fit-sizhe <sizhe.liu@fit-foxconn.com>
License: MIT
Requires-Python: >=3.8
License-File: LICENSE
Requires-Dist: PyPDF2>=3.0.0
Requires-Dist: pdfplumber>=0.9.0
Requires-Dist: markdown2>=2.4.8
Requires-Dist: weasyprint>=57.2.0
Requires-Dist: Pillow>=9.0.0
